{"description":"Verify Account not created for New Customer|Bank-Manager Login Add Customer","passed":false,"pending":false,"os":"windows","sessionId":"e9c57b6882e30b6217648e30ef0a1450","instanceId":26244,"browser":{"name":"chrome","version":"88.0.4324.96"},"message":["Error: ENOENT: no such file or directory, open 'C:\\Users\\PRAGYA\\js-eclipse-workspace\\XYZ Bank Project\\Screenshots\\22 14 25\\New_Customer_With_No_Account.png'"],"trace":["Error: ENOENT: no such file or directory, open 'C:\\Users\\PRAGYA\\js-eclipse-workspace\\XYZ Bank Project\\Screenshots\\22 14 25\\New_Customer_With_No_Account.png'"],"browserLogs":[],"screenShotFile":"00dd002d-00b1-0090-008a-007d00590002.png","timestamp":1611305807515,"duration":594}
